{
  "docs": {
    "Introduction": [
      "intro",
      "kin-architecture-overview",
      "friendbot",
      "appid"
    ],
    "Quick Start": [
      "quick-start/hi-kin-android",
      "quick-start/hi-kin-ios",
      "quick-start/hi-kin-python",
      "quick-start/hi-kin-unity"
    ],
    "Android": [
      "documentation/android-sdk",
      "documentation/android-api"
    ],
    "iOS": [
      "documentation/ios-sdk",
      "documentation/ios-api"
    ],
    "Python": [
      "documentation/python-sdk",
      "documentation/python-bootstrap"
    ],
    "Unity": [
      "documentation/unity-sdk"
    ]
  }
}
